{"cameraMode":{"drawMode":0,"name":"Shaded","section":"Shading Mode"},"sceneLighting":false,"audioPlay":false,"sceneViewState":{"showFog":true,"showMaterialUpdate":false,"showSkybox":false,"showFlares":true,"showImageEffects":true,"showParticleSystems":true},"in2DMode":false,"pivot":{"x":-6.903243064880371,"y":1.7089921236038209,"z":-23.61202049255371},"rotation":{"x":-0.10430159419775009,"y":0.8002845644950867,"z":-0.14588336646556855,"w":-0.5721755027770996},"size":1.4217809438705445,"orthographic":false}